smolsaml/__about__.py
smolsaml/__init__.py
smolsaml/consts.py
smolsaml/exceptions.py
smolsaml/login.py
smolsaml/response_validation.py
smolsaml/models/__init__.py
smolsaml/models/authn_request_configuration.py
smolsaml/models/http.py
smolsaml/models/idp_configuration.py
smolsaml/models/saml_assertion.py
smolsaml/models/saml_attribute.py
smolsaml/models/saml_name_id.py
smolsaml/models/saml_response.py
smolsaml/models/saml_status.py
smolsaml/models/saml_subject.py
smolsaml/models/sp_configuration.py
smolsaml/models/utils.py
smolsaml/utils/__init__.py
smolsaml/utils/data.py
smolsaml/utils/saml.py
smolsaml/utils/xml.py
smolsaml/xmlsec/__init__.py
smolsaml/xmlsec/exceptions.py
smolsaml/xmlsec/utils.py
smolsaml/xmlsec/verify.py
smolsaml-0.0.5.dist-info/METADATA
smolsaml-0.0.5.dist-info/WHEEL
smolsaml-0.0.5.dist-info/licenses/LICENSE.txt
smolsaml-0.0.5.dist-info/RECORD
