Metadata-Version: 2.1
Name: smolsaml
Version: 0.0.5
Project-URL: Documentation, https://github.com/akx/smolsaml#readme
Project-URL: Issues, https://github.com/akx/smolsaml/issues
Project-URL: Source, https://github.com/akx/smolsaml
Author-email: Aarni Koskela <akx@iki.fi>
License-Expression: MIT
License-File: LICENSE.txt
Classifier: Development Status :: 3 - Alpha
Classifier: Programming Language :: Python
Classifier: Programming Language :: Python :: 3.8
Classifier: Programming Language :: Python :: 3.9
Classifier: Programming Language :: Python :: 3.10
Classifier: Programming Language :: Python :: 3.11
Classifier: Programming Language :: Python :: Implementation :: CPython
Classifier: Programming Language :: Python :: Implementation :: PyPy
Requires-Python: >=3.8
Requires-Dist: xmltodict~=0.13.0
